{
	"period": {"to": ". ", "features": ["no_space_before", "cap_next", "no_period"]},
	"dot": {"to": ".", "features": ["no_space_before"]},
	"comma": {"to": ", ", "features": ["no_space_before", "no_period"]},
	"colon": {"to": ":", "features": ["no_space_before", "no_period"]},
	"semicolon": {"to": ";", "features": ["no_space_before", "no_period"]},
	"question mark": {"to": "? ", "features": ["no_space_before", "cap_next", "no_period"]},
	"exclamation point": {"to": "! ", "features": ["no_space_before", "cap_next", "no_period"]},
	"slash": {"to": "/", "features": ["no_space_before", "no_period"]},
	"backslash": {"to": "\\", "features": ["no_space_before", "no_period"]},
	"left quote": {"to": "\"", "features": ["no_period"]},
	"right quote": {"to": "\" ", "features": ["no_space_before"]},
	"dash": {"to": "-", "features": ["no_space_before", "no_period"]},
	"underscore": {"to": "_", "features": ["no_space_before", "no_period"]},
	"left bracket": {"to": "[", "features": ["no_period"]},
	"right bracket": {"to": "]", "features": ["no_space_before"]},
	"left brace": {"to": "{", "features": ["no_period"]},
	"right brace": {"to": "}", "features": ["no_space_before"]},
	"digit zero": {"to": "0"},
	"digit one": {"to": "1"},
	"digit two": {"to": "2"},
	"digit too": {"to": "2"},
	"digit to": {"to": "2"},
	"digit three": {"to": "3"},
	"digit four": {"to": "4"},
	"digit five": {"to": "5"},
	"digit six": {"to": "6"},
	"digit seven": {"to": "7"},
	"digit eight": {"to": "8"},
	"digit ate": {"to": "8"},
	"digit nine": {"to": "9"}
}
